LICENSE
MANIFEST.in
README.rst
setup.py
asyncdef.interfaces.egg-info/PKG-INFO
asyncdef.interfaces.egg-info/SOURCES.txt
asyncdef.interfaces.egg-info/dependency_links.txt
asyncdef.interfaces.egg-info/entry_points.txt
asyncdef.interfaces.egg-info/not-zip-safe
asyncdef.interfaces.egg-info/requires.txt
asyncdef.interfaces.egg-info/top_level.txt
asyncdef/interfaces/__init__.py
asyncdef/interfaces/emitter/__init__.py
asyncdef/interfaces/emitter/iemitter.py
asyncdef/interfaces/engine/__init__.py
asyncdef/interfaces/engine/icoroutine.py
asyncdef/interfaces/engine/iengine.py
asyncdef/interfaces/engine/iprocessor.py
asyncdef/interfaces/engine/iselector.py
asyncdef/interfaces/engine/itime.py