Metadata-Version: 1.0
Name: asyncdef.interfaces
Version: 0.2.1
Summary: Public APIs for the core asyncdef components.
Home-page: https://github.com/asyncdef/interfaces
Author: Kevin Conway
Author-email: kevinjacobconway@gmail.com
License: Apache 2.0
Platform: UNKNOWN
